CHANGES.md
MANIFEST.in
README.md
UNLICENSE
setup.cfg
setup.py
src/pyramid_raven/__init__.py
src/pyramid_raven/client.py
src/pyramid_raven/constants.py
src/pyramid_raven/panel.py
src/pyramid_raven.egg-info/PKG-INFO
src/pyramid_raven.egg-info/SOURCES.txt
src/pyramid_raven.egg-info/dependency_links.txt
src/pyramid_raven.egg-info/not-zip-safe
src/pyramid_raven.egg-info/requires.txt
src/pyramid_raven.egg-info/top_level.txt
src/pyramid_raven/templates/panel.mako